validator/__init__.py
validator.py-1.3.0.dist-info/LICENSE
validator.py-1.3.0.dist-info/METADATA
validator.py-1.3.0.dist-info/WHEEL
validator.py-1.3.0.dist-info/top_level.txt
validator.py-1.3.0.dist-info/RECORD
